{
  "id": "DCBEF2C9-E4F4-4929-82B2-EA7FC9166109",
  "name": "AzureWebPowerShellDeployment",
  "friendlyName": "Azure Web App Deployment",
  "description": "Publish a Visual Studio Web project to a Microsoft Azure Web App using Web Deploy",
  "helpMarkDown": "[More Information](http://go.microsoft.com/fwlink/?LinkID=613750)",
  "category": "Deploy",
  "visibility": [
                "Build",
                "Release"
                ],
  "author": "Microsoft Corporation",
  "version": {
    "Major": 1,
    "Minor": 0,
    "Patch": 20
  },
  "demands": [
    "azureps"
  ],
  "minimumAgentVersion": "1.90.0",
  "inputs": [
    {
      "name": "ConnectedServiceName",
      "type": "connectedService:Azure:Certificate,UsernamePassword",
      "label": "Azure Subscription",
      "defaultValue": "",
      "required": true,
      "helpMarkDown": "Azure subscription to target for deployment."
    },
    {
      "name": "WebSiteName",
      "type": "pickList",
      "label": "Web App Name",
      "defaultValue": "",
      "required": true
    },
    {
      "name": "WebSiteLocation",
      "type": "pickList",
      "label": "Web App Location",
      "defaultValue": "South Central US",
      "required": true,
      "helpMarkDown": "Select a region for deployment.",
      "options": {
        "Australia East": "Australia East",
        "Australia Southeast": "Australia Southeast",
        "Brazil South": "Brazil South",
        "Central US": "Central US",
        "East Asia": "East Asia",
        "East US": "East US",
        "East US2": "East US2",
        "Japan East": "Japan East",
        "Japan West": "Japan West",
        "North Central US": "North Central US",
        "North Europe": "North Europe",
        "South Central US": "South Central US",
        "Southeast Asia": "Southeast Asia",
        "West Europe": "West Europe",
        "West US": "West US"
      },
      "properties": {
        "EditableOptions": "True"
      }
    },
    {
      "name": "Slot",
      "type": "string",
      "label": "Slot",
      "defaultValue": "",
      "required": false,
      "helpMarkDown": "Slot"
    },
    {
      "name": "Package",
      "type": "filePath",
      "label": "Web Deploy Package",
      "defaultValue": "",
      "helpMarkDown": "Path to the Visual Studio Web Deploy package under the default artifact directory.",
      "required": true
    },
    {
      "name": "AdditionalArguments",
      "type": "string",
      "label": "Additional Arguments",
      "defaultValue": "",
      "required": false
    }
  ],
  "sourceDefinitions": [
    {
        "target": "WebSiteName",
        "endpoint": "https://management.core.windows.net/$(authKey.SubscriptionId)/services/webspaces/$(WebSiteLocation)Webspace/sites",
        "selector": "xpath://Site/Name",
        "authKey": "$(ConnectedServiceName)"
    }
  ],
  "instanceNameFormat": "Azure Deployment: $(WebSiteName)",
  "execution": {
    "AzurePowerShell": {
      "target": "$(currentDirectory)\\Publish-AzureWebDeployment.ps1",
      "argumentFormat": "",
      "workingDirectory": "$(currentDirectory)"
    }
  }
}
